odsgenerator/__init__.py
odsgenerator/cli.py
odsgenerator/odsgenerator.py
odsgenerator-1.12.0.dist-info/WHEEL
odsgenerator-1.12.0.dist-info/entry_points.txt
odsgenerator-1.12.0.dist-info/METADATA
odsgenerator-1.12.0.dist-info/RECORD
