Metadata-Version: 2.4
Name: odsgenerator
Version: 1.12.0
Summary: Generate an OpenDocument Format .ods file from json or yaml file
Keywords: openDocument,ODF,ods,json,spreadsheet,generator
Author: Jérôme Dumonteil
Author-email: Jérôme Dumonteil <jerome.dumonteil@gmail.com>
License-Expression: MIT
Classifier: Development Status :: 5 - Production/Stable
Classifier: Environment :: Console
Classifier: Intended Audience :: Developers
Classifier: License :: OSI Approved :: MIT License
Classifier: Programming Language :: Python
Classifier: Programming Language :: Python :: 3
Classifier: Programming Language :: Python :: 3 :: Only
Classifier: Programming Language :: Python :: 3.10
Classifier: Programming Language :: Python :: 3.11
Classifier: Programming Language :: Python :: 3.12
Classifier: Programming Language :: Python :: 3.13
Classifier: Programming Language :: Python :: 3.14
Classifier: Operating System :: OS Independent
Classifier: Topic :: Text Processing
Classifier: Topic :: Software Development :: Libraries :: Python Modules
Requires-Dist: odfdo>=3.7.7
Requires-Dist: pyyaml>=6.0.3
Requires-Python: >=3.10, <4
Project-URL: Homepage, https://github.com/jdum/odsgenerator
Project-URL: Repository, https://github.com/jdum/odsgenerator
